{
    "ElementName":"Module",
    "breakPointInfo":{
        "disabled":false,
        "hasBreakPoint":false,
        "type":2
    },
    "displayName":"我的地图",
    "flags":{
        "enableDisplayName":true
    },
    "folder":{
        "ElementName":"Folder",
        "breakPointInfo":{
            "disabled":false,
            "hasBreakPoint":false,
            "type":2
        },
        "contents":{
            "__TYPE":"Array",
            "contents":[
                {
                    "ElementName":"Source",
                    "targetUninit":{
                        "id":"Trigger:ll:3509013233",
                        "packageName":"busiyixiantu_5n1b",
                        "s_or_c":"server"
                    }
                },
                {
                    "ElementName":"Folder",
                    "breakPointInfo":{
                        "disabled":false,
                        "hasBreakPoint":false,
                        "type":2
                    },
                    "contents":{
                        "__TYPE":"Array",
                        "contents":[
                            {
                                "ElementName":"Source",
                                "targetUninit":{
                                    "id":"Variable:小黑鸟大数量:2729547333",
                                    "packageName":"busiyixiantu_5n1b",
                                    "s_or_c":"server"
                                }
                            },
                            {
                                "ElementName":"Source",
                                "targetUninit":{
                                    "id":"CustomEvent:修改UI文字:2239314731",
                                    "packageName":"busiyixiantu_5n1b",
                                    "s_or_c":"server"
                                }
                            },
                            {
                                "ElementName":"Source",
                                "targetUninit":{
                                    "id":"CustomEvent:大黑鸟死亡事件:3890935409",
                                    "packageName":"busiyixiantu_5n1b",
                                    "s_or_c":"server"
                                }
                            },
                            {
                                "ElementName":"Source",
                                "targetUninit":{
                                    "id":"Trigger:移动到大黑鸟:2682711118",
                                    "packageName":"busiyixiantu_5n1b",
                                    "s_or_c":"server"
                                }
                            },
                            {
                                "ElementName":"Source",
                                "targetUninit":{
                                    "id":"Trigger:大黑鸟死亡:258120875",
                                    "packageName":"busiyixiantu_5n1b",
                                    "s_or_c":"server"
                                }
                            },
                            {
                                "ElementName":"Source",
                                "targetUninit":{
                                    "id":"Trigger:玩家单位设置初始化:2554616435",
                                    "packageName":"busiyixiantu_5n1b",
                                    "s_or_c":"server"
                                }
                            }
                        ]
                    },
                    "displayName":"",
                    "flags":{
                    },
                    "name":"新手指引",
                    "rankOrder":2,
                    "staticWarningMsgs":{
                        "__TYPE":"Array",
                        "contents":{
                        }
                    },
                    "tips":""
                },
                {
                    "ElementName":"Folder",
                    "breakPointInfo":{
                        "disabled":false,
                        "hasBreakPoint":false,
                        "type":2
                    },
                    "contents":{
                        "__TYPE":"Array",
                        "contents":[
                            {
                                "ElementName":"Source",
                                "targetUninit":{
                                    "id":"Variable:玩家的主控单位:1872362639",
                                    "packageName":"busiyixiantu_5n1b",
                                    "s_or_c":"server"
                                }
                            },
                            {
                                "ElementName":"Source",
                                "targetUninit":{
                                    "id":"Variable:是否在主城:1852693884",
                                    "packageName":"busiyixiantu_5n1b",
                                    "s_or_c":"server"
                                }
                            }
                        ]
                    },
                    "displayName":"",
                    "flags":{
                    },
                    "name":"通用变量",
                    "rankOrder":3,
                    "staticWarningMsgs":{
                        "__TYPE":"Array",
                        "contents":{
                        }
                    },
                    "tips":""
                },
                {
                    "ElementName":"Folder",
                    "breakPointInfo":{
                        "disabled":false,
                        "hasBreakPoint":false,
                        "type":2
                    },
                    "contents":{
                        "__TYPE":"Array",
                        "contents":[
                            {
                                "ElementName":"Source",
                                "targetUninit":{
                                    "id":"Variable:加怪的怪物类型:3316058467",
                                    "packageName":"busiyixiantu_5n1b",
                                    "s_or_c":"server"
                                }
                            },
                            {
                                "ElementName":"Source",
                                "targetUninit":{
                                    "id":"Variable:刷怪判定:1742202236",
                                    "packageName":"busiyixiantu_5n1b",
                                    "s_or_c":"server"
                                }
                            },
                            {
                                "ElementName":"Source",
                                "targetUninit":{
                                    "id":"Variable:刷怪数量:1604587751",
                                    "packageName":"busiyixiantu_5n1b",
                                    "s_or_c":"server"
                                }
                            },
                            {
                                "ElementName":"Source",
                                "targetUninit":{
                                    "id":"Variable:加怪记录:142094784",
                                    "packageName":"busiyixiantu_5n1b",
                                    "s_or_c":"server"
                                }
                            },
                            {
                                "ElementName":"Source",
                                "targetUninit":{
                                    "id":"Variable:加怪升级记录:1775366086",
                                    "packageName":"busiyixiantu_5n1b",
                                    "s_or_c":"server"
                                }
                            },
                            {
                                "ElementName":"Source",
                                "targetUninit":{
                                    "id":"Variable:加怪死亡计数:83164160",
                                    "packageName":"busiyixiantu_5n1b",
                                    "s_or_c":"server"
                                }
                            },
                            {
                                "ElementName":"Source",
                                "targetUninit":{
                                    "id":"Variable:是否在加怪升级中:1417585454",
                                    "packageName":"busiyixiantu_5n1b",
                                    "s_or_c":"server"
                                }
                            },
                            {
                                "ElementName":"Source",
                                "targetUninit":{
                                    "id":"Variable:每关刷的怪:3033276193",
                                    "packageName":"busiyixiantu_5n1b",
                                    "s_or_c":"server"
                                }
                            },
                            {
                                "ElementName":"Source",
                                "targetUninit":{
                                    "id":"Variable:升级怪总数据:2723181533",
                                    "packageName":"busiyixiantu_5n1b",
                                    "s_or_c":"server"
                                }
                            },
                            {
                                "ElementName":"Source",
                                "targetUninit":{
                                    "id":"Variable:当前关卡刷怪数据:101370761",
                                    "packageName":"busiyixiantu_5n1b",
                                    "s_or_c":"server"
                                }
                            },
                            {
                                "ElementName":"Source",
                                "targetUninit":{
                                    "id":"Variable:存在刷怪计时器:1692124367",
                                    "packageName":"busiyixiantu_5n1b",
                                    "s_or_c":"server"
                                }
                            },
                            {
                                "ElementName":"Source",
                                "targetUninit":{
                                    "id":"CustomEvent:加怪了:2734450391",
                                    "packageName":"busiyixiantu_5n1b",
                                    "s_or_c":"server"
                                }
                            },
                            {
                                "ElementName":"Source",
                                "targetUninit":{
                                    "id":"CustomEvent:不能再减怪了:696085918",
                                    "packageName":"busiyixiantu_5n1b",
                                    "s_or_c":"server"
                                }
                            },
                            {
                                "ElementName":"Source",
                                "targetUninit":{
                                    "id":"CustomEvent:加怪挑战中:1737037326",
                                    "packageName":"busiyixiantu_5n1b",
                                    "s_or_c":"server"
                                }
                            },
                            {
                                "ElementName":"Source",
                                "targetUninit":{
                                    "id":"CustomEvent:加怪完成或者失败:2961502349",
                                    "packageName":"busiyixiantu_5n1b",
                                    "s_or_c":"server"
                                }
                            },
                            {
                                "ElementName":"Source",
                                "targetUninit":{
                                    "id":"CustomEvent:减怪UI:1374304323",
                                    "packageName":"busiyixiantu_5n1b",
                                    "s_or_c":"server"
                                }
                            },
                            {
                                "ElementName":"Source",
                                "targetUninit":{
                                    "id":"Trigger:刷怪:2162209189",
                                    "packageName":"busiyixiantu_5n1b",
                                    "s_or_c":"server"
                                }
                            },
                            {
                                "ElementName":"Source",
                                "targetUninit":{
                                    "id":"Trigger:玩家受伤:2039771746",
                                    "packageName":"busiyixiantu_5n1b",
                                    "s_or_c":"server"
                                }
                            },
                            {
                                "ElementName":"Source",
                                "targetUninit":{
                                    "id":"Trigger:玩家死亡:3115440447",
                                    "packageName":"busiyixiantu_5n1b",
                                    "s_or_c":"server"
                                }
                            },
                            {
                                "ElementName":"Source",
                                "targetUninit":{
                                    "id":"Trigger:进入修炼室:467784541",
                                    "packageName":"busiyixiantu_5n1b",
                                    "s_or_c":"server"
                                }
                            },
                            {
                                "ElementName":"Source",
                                "targetUninit":{
                                    "id":"Trigger:加怪:2883850992",
                                    "packageName":"busiyixiantu_5n1b",
                                    "s_or_c":"server"
                                }
                            },
                            {
                                "ElementName":"Source",
                                "targetUninit":{
                                    "id":"Trigger:减怪:185380628",
                                    "packageName":"busiyixiantu_5n1b",
                                    "s_or_c":"server"
                                }
                            },
                            {
                                "ElementName":"Source",
                                "targetUninit":{
                                    "id":"Trigger:加怪的通关判定:2437491098",
                                    "packageName":"busiyixiantu_5n1b",
                                    "s_or_c":"server"
                                }
                            }
                        ]
                    },
                    "displayName":"",
                    "flags":{
                    },
                    "name":"修炼室",
                    "rankOrder":4,
                    "s_or_c":"server",
                    "staticWarningMsgs":{
                        "__TYPE":"Array",
                        "contents":{
                        }
                    },
                    "tips":""
                },
                {
                    "ElementName":"Folder",
                    "breakPointInfo":{
                        "disabled":false,
                        "hasBreakPoint":false,
                        "type":2
                    },
                    "contents":{
                        "__TYPE":"Array",
                        "contents":[
                            {
                                "ElementName":"Source",
                                "targetUninit":{
                                    "id":"Trigger:攻击力修改:2417426209",
                                    "packageName":"busiyixiantu_5n1b",
                                    "s_or_c":"server"
                                }
                            }
                        ]
                    },
                    "displayName":"",
                    "flags":{
                    },
                    "name":"属性修改",
                    "rankOrder":5,
                    "staticWarningMsgs":{
                        "__TYPE":"Array",
                        "contents":{
                        }
                    },
                    "tips":""
                },
                {
                    "ElementName":"Folder",
                    "breakPointInfo":{
                        "disabled":false,
                        "hasBreakPoint":false,
                        "type":2
                    },
                    "contents":{
                        "__TYPE":"Array",
                        "contents":[
                            {
                                "ElementName":"Source",
                                "targetUninit":{
                                    "id":"Trigger:等级突破:1865569901",
                                    "packageName":"busiyixiantu_5n1b",
                                    "s_or_c":"server"
                                }
                            },
                            {
                                "ElementName":"Source",
                                "targetUninit":{
                                    "id":"Trigger:刷突破BOSS:1925143624",
                                    "packageName":"busiyixiantu_5n1b",
                                    "s_or_c":"server"
                                }
                            },
                            {
                                "ElementName":"Source",
                                "targetUninit":{
                                    "id":"Trigger:等级突破BOSS死亡:784660315",
                                    "packageName":"busiyixiantu_5n1b",
                                    "s_or_c":"server"
                                }
                            },
                            {
                                "ElementName":"Source",
                                "targetUninit":{
                                    "id":"Trigger:等级突破启用:2632384149",
                                    "packageName":"busiyixiantu_5n1b",
                                    "s_or_c":"server"
                                }
                            },
                            {
                                "ElementName":"Source",
                                "targetUninit":{
                                    "id":"Variable:等级数组:2021923286",
                                    "packageName":"busiyixiantu_5n1b",
                                    "s_or_c":"server"
                                }
                            },
                            {
                                "ElementName":"Source",
                                "targetUninit":{
                                    "id":"Variable:玩家当前等级阶层:3540915512",
                                    "packageName":"busiyixiantu_5n1b",
                                    "s_or_c":"server"
                                }
                            },
                            {
                                "ElementName":"Source",
                                "targetUninit":{
                                    "id":"Variable:BOSS怪物列表:1552172187",
                                    "packageName":"busiyixiantu_5n1b",
                                    "s_or_c":"server"
                                }
                            },
                            {
                                "ElementName":"Source",
                                "targetUninit":{
                                    "id":"Variable:是否在挑战等级突破BOSS:4191588095",
                                    "packageName":"busiyixiantu_5n1b",
                                    "s_or_c":"server"
                                }
                            },
                            {
                                "ElementName":"Source",
                                "targetUninit":{
                                    "id":"Variable:达到当前最高等级:2673637037",
                                    "packageName":"busiyixiantu_5n1b",
                                    "s_or_c":"server"
                                }
                            },
                            {
                                "ElementName":"Source",
                                "targetUninit":{
                                    "id":"Variable:特殊等级限制:1634921449",
                                    "packageName":"busiyixiantu_5n1b",
                                    "s_or_c":"server"
                                }
                            },
                            {
                                "ElementName":"Source",
                                "targetUninit":{
                                    "id":"CustomEvent:等级突破显示:2322663292",
                                    "packageName":"busiyixiantu_5n1b",
                                    "s_or_c":"server"
                                }
                            },
                            {
                                "ElementName":"Source",
                                "targetUninit":{
                                    "id":"CustomEvent:显示等级:4054146341",
                                    "packageName":"busiyixiantu_5n1b",
                                    "s_or_c":"server"
                                }
                            }
                        ]
                    },
                    "displayName":"",
                    "flags":{
                    },
                    "name":"等级突破",
                    "rankOrder":6,
                    "s_or_c":"server",
                    "staticWarningMsgs":{
                        "__TYPE":"Array",
                        "contents":{
                        }
                    },
                    "tips":""
                },
                {
                    "ElementName":"Folder",
                    "breakPointInfo":{
                        "disabled":false,
                        "hasBreakPoint":false,
                        "type":2
                    },
                    "contents":{
                        "__TYPE":"Array",
                        "contents":[
                            {
                                "ElementName":"Source",
                                "targetUninit":{
                                    "id":"FunctionDefine:清除怪物:1430479131",
                                    "packageName":"busiyixiantu_5n1b",
                                    "s_or_c":"server"
                                }
                            },
                            {
                                "ElementName":"Source",
                                "targetUninit":{
                                    "id":"FunctionDefine:给玩家升仙令:4211356085",
                                    "packageName":"busiyixiantu_5n1b",
                                    "s_or_c":"server"
                                }
                            },
                            {
                                "ElementName":"Source",
                                "targetUninit":{
                                    "id":"FunctionDefine:修改玩家攻击距离:874396032",
                                    "packageName":"busiyixiantu_5n1b",
                                    "s_or_c":"server"
                                }
                            },
                            {
                                "ElementName":"Source",
                                "targetUninit":{
                                    "id":"FunctionDefine:进入修炼室和修改UI:87145107",
                                    "packageName":"busiyixiantu_5n1b",
                                    "s_or_c":"server"
                                }
                            }
                        ]
                    },
                    "displayName":"",
                    "flags":{
                    },
                    "name":"通用函数",
                    "rankOrder":7,
                    "s_or_c":"server",
                    "staticWarningMsgs":{
                        "__TYPE":"Array",
                        "contents":{
                        }
                    },
                    "tips":""
                },
                {
                    "ElementName":"Folder",
                    "breakPointInfo":{
                        "disabled":false,
                        "hasBreakPoint":false,
                        "type":2
                    },
                    "contents":{
                        "__TYPE":"Array",
                        "contents":[
                            {
                                "ElementName":"Source",
                                "targetUninit":{
                                    "id":"Trigger:trg挑战注册:3811029683",
                                    "packageName":"busiyixiantu_5n1b",
                                    "s_or_c":"server"
                                }
                            },
                            {
                                "ElementName":"Source",
                                "targetUninit":{
                                    "id":"Trigger:挑战退出:2941740800",
                                    "packageName":"busiyixiantu_5n1b",
                                    "s_or_c":"server"
                                }
                            },
                            {
                                "ElementName":"Source",
                                "targetUninit":{
                                    "id":"Trigger:镜头跟随:1639203560",
                                    "packageName":"busiyixiantu_5n1b",
                                    "s_or_c":"server"
                                }
                            },
                            {
                                "ElementName":"Source",
                                "targetUninit":{
                                    "id":"Trigger:主线挑战属性奖励:2046688947",
                                    "packageName":"busiyixiantu_5n1b",
                                    "s_or_c":"server"
                                }
                            },
                            {
                                "ElementName":"Source",
                                "targetUninit":{
                                    "id":"CustomEvent:客户端关闭爬塔UI:698372840",
                                    "packageName":"busiyixiantu_5n1b",
                                    "s_or_c":"server"
                                }
                            },
                            {
                                "ElementName":"Source",
                                "targetUninit":{
                                    "id":"CustomEvent:主线挑战完成:4135326807",
                                    "packageName":"busiyixiantu_5n1b",
                                    "s_or_c":"server"
                                }
                            }
                        ]
                    },
                    "displayName":"",
                    "flags":{
                    },
                    "name":"挑战",
                    "rankOrder":8,
                    "staticWarningMsgs":{
                        "__TYPE":"Array",
                        "contents":{
                        }
                    },
                    "tips":""
                },
                {
                    "ElementName":"Folder",
                    "breakPointInfo":{
                        "disabled":false,
                        "hasBreakPoint":false,
                        "type":2
                    },
                    "contents":{
                        "__TYPE":"Array",
                        "contents":[
                            {
                                "ElementName":"Source",
                                "targetUninit":{
                                    "id":"FunctionDefine:func_测试面板注册按钮:2394943000",
                                    "packageName":"busiyixiantu_5n1b",
                                    "s_or_c":"server"
                                }
                            },
                            {
                                "ElementName":"Source",
                                "targetUninit":{
                                    "id":"FunctionDefine:func_测试面板注册按钮:2394943000",
                                    "packageName":"busiyixiantu_5n1b",
                                    "s_or_c":"server"
                                }
                            },
                            {
                                "ElementName":"Source",
                                "targetUninit":{
                                    "id":"FunctionDefine:func_创建rpg_挑战:3631981537",
                                    "packageName":"busiyixiantu_5n1b",
                                    "s_or_c":"server"
                                }
                            },
                            {
                                "ElementName":"Source",
                                "targetUninit":{
                                    "id":"FunctionDefine:func_创建mxh_挑战:3631981537",
                                    "packageName":"busiyixiantu_5n1b",
                                    "s_or_c":"server"
                                }
                            }
                        ]
                    },
                    "displayName":"",
                    "flags":{
                    },
                    "name":"函数",
                    "rankOrder":9,
                    "s_or_c":"server",
                    "staticWarningMsgs":{
                        "__TYPE":"Array",
                        "contents":{
                        }
                    },
                    "tips":""
                },
                {
                    "ElementName":"Folder",
                    "breakPointInfo":{
                        "disabled":false,
                        "hasBreakPoint":false,
                        "type":2
                    },
                    "contents":{
                        "__TYPE":"Array",
                        "contents":[
                            {
                                "ElementName":"Source",
                                "targetUninit":{
                                    "id":"Class:rpg_challenge:2515388537",
                                    "packageName":"busiyixiantu_5n1b",
                                    "s_or_c":"server"
                                }
                            }
                        ]
                    },
                    "displayName":"",
                    "flags":{
                    },
                    "name":"类",
                    "rankOrder":10,
                    "s_or_c":"server",
                    "staticWarningMsgs":{
                        "__TYPE":"Array",
                        "contents":{
                        }
                    },
                    "tips":""
                },
                {
                    "ElementName":"Folder",
                    "breakPointInfo":{
                        "disabled":false,
                        "hasBreakPoint":false,
                        "type":2
                    },
                    "contents":{
                        "__TYPE":"Array",
                        "contents":[
                            {
                                "ElementName":"Source",
                                "targetUninit":{
                                    "id":"Class:玩家数据:588543521",
                                    "packageName":"busiyixiantu_5n1b",
                                    "s_or_c":"server"
                                }
                            }
                        ]
                    },
                    "displayName":"",
                    "flags":{
                    },
                    "name":"云变量",
                    "rankOrder":11,
                    "s_or_c":"server",
                    "staticWarningMsgs":{
                        "__TYPE":"Array",
                        "contents":{
                        }
                    },
                    "tips":""
                },
                {
                    "ElementName":"Folder",
                    "breakPointInfo":{
                        "disabled":false,
                        "hasBreakPoint":false,
                        "type":2
                    },
                    "contents":{
                        "__TYPE":"Array",
                        "contents":[
                            {
                                "ElementName":"Source",
                                "targetUninit":{
                                    "id":"CustomEvent:玩家_rpg挑战开始:3488048439",
                                    "packageName":"busiyixiantu_5n1b",
                                    "s_or_c":"server"
                                }
                            },
                            {
                                "ElementName":"Source",
                                "targetUninit":{
                                    "id":"CustomEvent:玩家_完成rpg挑战自动退出:4086149018",
                                    "packageName":"busiyixiantu_5n1b",
                                    "s_or_c":"server"
                                }
                            },
                            {
                                "ElementName":"Source",
                                "targetUninit":{
                                    "id":"CustomEvent:造成伤害前:3450482188",
                                    "packageName":"busiyixiantu_5n1b",
                                    "s_or_c":"server"
                                }
                            },
                            {
                                "ElementName":"Source",
                                "targetUninit":{
                                    "id":"CustomEvent:主线任务关闭ui:2187034412",
                                    "packageName":"busiyixiantu_5n1b",
                                    "s_or_c":"server"
                                }
                            },
                            {
                                "ElementName":"Source",
                                "targetUninit":{
                                    "id":"CustomEvent:升仙令挑战:3758319742",
                                    "packageName":"busiyixiantu_5n1b",
                                    "s_or_c":"server"
                                }
                            },
                            {
                                "ElementName":"Source",
                                "targetUninit":{
                                    "id":"CustomEvent:打开修炼室UI:1866322789",
                                    "packageName":"busiyixiantu_5n1b",
                                    "s_or_c":"server"
                                }
                            },
                            {
                                "ElementName":"Source",
                                "targetUninit":{
                                    "id":"CustomEvent:进入修炼室消息事件:4167310315",
                                    "packageName":"busiyixiantu_5n1b",
                                    "s_or_c":"server"
                                }
                            },
                            {
                                "ElementName":"Source",
                                "targetUninit":{
                                    "id":"CustomEvent:特殊UI修改需求服务器端:1043714473",
                                    "packageName":"busiyixiantu_5n1b",
                                    "s_or_c":"server"
                                }
                            }
                        ]
                    },
                    "displayName":"",
                    "flags":{
                    },
                    "name":"通用事件",
                    "rankOrder":12,
                    "s_or_c":"server",
                    "staticWarningMsgs":{
                        "__TYPE":"Array",
                        "contents":{
                        }
                    },
                    "tips":""
                },
                {
                    "ElementName":"Folder",
                    "breakPointInfo":{
                        "disabled":false,
                        "hasBreakPoint":false,
                        "type":2
                    },
                    "contents":{
                        "__TYPE":"Array",
                        "contents":[
                            {
                                "ElementName":"Folder",
                                "breakPointInfo":{
                                    "disabled":false,
                                    "hasBreakPoint":false,
                                    "type":2
                                },
                                "contents":{
                                    "__TYPE":"Array",
                                    "contents":[
                                        {
                                            "ElementName":"Source",
                                            "targetUninit":{
                                                "id":"Trigger:玩家单位属性更新:3716584107",
                                                "packageName":"busiyixiantu_5n1b",
                                                "s_or_c":"server"
                                            }
                                        },
                                        {
                                            "ElementName":"Source",
                                            "targetUninit":{
                                                "id":"FunctionDefine:玩家单位属性计算:4257329517",
                                                "packageName":"busiyixiantu_5n1b",
                                                "s_or_c":"server"
                                            }
                                        }
                                    ]
                                },
                                "displayName":"",
                                "flags":{
                                },
                                "name":"属性计算",
                                "rankOrder":1,
                                "staticWarningMsgs":{
                                    "__TYPE":"Array",
                                    "contents":{
                                    }
                                },
                                "tips":""
                            },
                            {
                                "ElementName":"Folder",
                                "breakPointInfo":{
                                    "disabled":false,
                                    "hasBreakPoint":false,
                                    "type":2
                                },
                                "contents":{
                                    "__TYPE":"Array",
                                    "contents":[
                                        {
                                            "ElementName":"Source",
                                            "targetUninit":{
                                                "id":"FunctionDefine:普攻伤害计算:1976764396",
                                                "packageName":"busiyixiantu_5n1b",
                                                "s_or_c":"server"
                                            }
                                        },
                                        {
                                            "ElementName":"Source",
                                            "targetUninit":{
                                                "id":"FunctionDefine:物理技能伤害计算:3330287128",
                                                "packageName":"busiyixiantu_5n1b",
                                                "s_or_c":"server"
                                            }
                                        },
                                        {
                                            "ElementName":"Source",
                                            "targetUninit":{
                                                "id":"FunctionDefine:法术技能伤害计算:3072685222",
                                                "packageName":"busiyixiantu_5n1b",
                                                "s_or_c":"server"
                                            }
                                        }
                                    ]
                                },
                                "displayName":"",
                                "flags":{
                                },
                                "name":"伤害计算",
                                "rankOrder":2,
                                "staticWarningMsgs":{
                                    "__TYPE":"Array",
                                    "contents":{
                                    }
                                },
                                "tips":""
                            },
                            {
                                "ElementName":"Source",
                                "targetUninit":{
                                    "id":"Trigger:攻击回血:1795625569",
                                    "packageName":"busiyixiantu_5n1b",
                                    "s_or_c":"server"
                                }
                            }
                        ]
                    },
                    "displayName":"",
                    "flags":{
                    },
                    "name":"数值计算",
                    "rankOrder":13,
                    "s_or_c":"server",
                    "staticWarningMsgs":{
                        "__TYPE":"Array",
                        "contents":{
                        }
                    },
                    "tips":""
                },
                {
                    "ElementName":"Folder",
                    "breakPointInfo":{
                        "disabled":false,
                        "hasBreakPoint":false,
                        "type":2
                    },
                    "contents":{
                        "__TYPE":"Array",
                        "contents":[
                            {
                                "ElementName":"Source",
                                "targetUninit":{
                                    "id":"CustomEvent:升仙令挑战完成:1494579436",
                                    "packageName":"busiyixiantu_5n1b",
                                    "s_or_c":"server"
                                }
                            },
                            {
                                "ElementName":"Source",
                                "targetUninit":{
                                    "id":"CustomEvent:升仙令选择主属性:2573131131",
                                    "packageName":"busiyixiantu_5n1b",
                                    "s_or_c":"server"
                                }
                            },
                            {
                                "ElementName":"Source",
                                "targetUninit":{
                                    "id":"CustomEvent:升仙令客户端消息:3531887812",
                                    "packageName":"busiyixiantu_5n1b",
                                    "s_or_c":"server"
                                }
                            },
                            {
                                "ElementName":"Source",
                                "targetUninit":{
                                    "id":"Variable:升仙令等级:2878855943",
                                    "packageName":"busiyixiantu_5n1b",
                                    "s_or_c":"server"
                                }
                            },
                            {
                                "ElementName":"Source",
                                "targetUninit":{
                                    "id":"Trigger:升仙令:3588874703",
                                    "packageName":"busiyixiantu_5n1b",
                                    "s_or_c":"server"
                                }
                            },
                            {
                                "ElementName":"Source",
                                "targetUninit":{
                                    "id":"Trigger:升仙令挑战开始:3496285145",
                                    "packageName":"busiyixiantu_5n1b",
                                    "s_or_c":"server"
                                }
                            }
                        ]
                    },
                    "displayName":"",
                    "flags":{
                    },
                    "name":"升仙令配置",
                    "rankOrder":14,
                    "staticWarningMsgs":{
                        "__TYPE":"Array",
                        "contents":{
                        }
                    },
                    "tips":""
                },
                {
                    "ElementName":"Folder",
                    "breakPointInfo":{
                        "disabled":false,
                        "hasBreakPoint":false,
                        "type":2
                    },
                    "contents":{
                        "__TYPE":"Array",
                        "contents":[
                            {
                                "ElementName":"Source",
                                "targetUninit":{
                                    "id":"Trigger:合成装备:2983084093",
                                    "packageName":"busiyixiantu_5n1b",
                                    "s_or_c":"server"
                                }
                            }
                        ]
                    },
                    "displayName":"",
                    "flags":{
                    },
                    "name":"合成装备",
                    "rankOrder":15,
                    "staticWarningMsgs":{
                        "__TYPE":"Array",
                        "contents":{
                        }
                    },
                    "tips":""
                },
                {
                    "ElementName":"Folder",
                    "breakPointInfo":{
                        "disabled":false,
                        "hasBreakPoint":false,
                        "type":2
                    },
                    "contents":{
                        "__TYPE":"Array",
                        "contents":[
                            {
                                "ElementName":"Source",
                                "targetUninit":{
                                    "id":"Trigger:怪物进攻:143283455",
                                    "packageName":"busiyixiantu_5n1b",
                                    "s_or_c":"server"
                                }
                            },
                            {
                                "ElementName":"Source",
                                "targetUninit":{
                                    "id":"Trigger:返回主城:181516983",
                                    "packageName":"busiyixiantu_5n1b",
                                    "s_or_c":"server"
                                }
                            },
                            {
                                "ElementName":"Source",
                                "targetUninit":{
                                    "id":"Trigger:游戏失败:2846206796",
                                    "packageName":"busiyixiantu_5n1b",
                                    "s_or_c":"server"
                                }
                            },
                            {
                                "ElementName":"Source",
                                "targetUninit":{
                                    "id":"Trigger:游戏胜利:1869032360",
                                    "packageName":"busiyixiantu_5n1b",
                                    "s_or_c":"server"
                                }
                            },
                            {
                                "ElementName":"Source",
                                "targetUninit":{
                                    "id":"Trigger:退出游戏:3124913665",
                                    "packageName":"busiyixiantu_5n1b",
                                    "s_or_c":"server"
                                }
                            },
                            {
                                "ElementName":"Source",
                                "targetUninit":{
                                    "id":"Variable:进攻怪总数据:71808410",
                                    "packageName":"busiyixiantu_5n1b",
                                    "s_or_c":"server"
                                }
                            },
                            {
                                "ElementName":"Source",
                                "targetUninit":{
                                    "id":"Variable:当前进攻关卡刷怪数据:44412515",
                                    "packageName":"busiyixiantu_5n1b",
                                    "s_or_c":"server"
                                }
                            },
                            {
                                "ElementName":"Source",
                                "targetUninit":{
                                    "id":"Variable:进攻怪关数:2235925510",
                                    "packageName":"busiyixiantu_5n1b",
                                    "s_or_c":"server"
                                }
                            },
                            {
                                "ElementName":"Source",
                                "targetUninit":{
                                    "id":"CustomEvent:进攻怪消息:1037639151",
                                    "packageName":"busiyixiantu_5n1b",
                                    "s_or_c":"server"
                                }
                            },
                            {
                                "ElementName":"Source",
                                "targetUninit":{
                                    "id":"CustomEvent:游戏失败消息:196154388",
                                    "packageName":"busiyixiantu_5n1b",
                                    "s_or_c":"server"
                                }
                            },
                            {
                                "ElementName":"Source",
                                "targetUninit":{
                                    "id":"CustomEvent:游戏胜利消息:2002697930",
                                    "packageName":"busiyixiantu_5n1b",
                                    "s_or_c":"server"
                                }
                            }
                        ]
                    },
                    "displayName":"",
                    "flags":{
                    },
                    "name":"守城",
                    "rankOrder":16,
                    "s_or_c":"server",
                    "staticWarningMsgs":{
                        "__TYPE":"Array",
                        "contents":{
                        }
                    },
                    "tips":""
                },
                {
                    "ElementName":"Folder",
                    "breakPointInfo":{
                        "disabled":false,
                        "hasBreakPoint":false,
                        "type":2
                    },
                    "contents":{
                        "__TYPE":"Array",
                        "contents":[
                            {
                                "ElementName":"Source",
                                "targetUninit":{
                                    "id":"Trigger:爬塔镜头跟随:983219617",
                                    "packageName":"busiyixiantu_5n1b",
                                    "s_or_c":"server"
                                }
                            },
                            {
                                "ElementName":"Source",
                                "targetUninit":{
                                    "id":"Trigger:创建挑战:576855661",
                                    "packageName":"busiyixiantu_5n1b",
                                    "s_or_c":"server"
                                }
                            }
                        ]
                    },
                    "displayName":"",
                    "flags":{
                    },
                    "name":"爬塔",
                    "rankOrder":17,
                    "staticWarningMsgs":{
                        "__TYPE":"Array",
                        "contents":{
                        }
                    },
                    "tips":""
                },
                {
                    "ElementName":"Folder",
                    "breakPointInfo":{
                        "disabled":false,
                        "hasBreakPoint":false,
                        "type":2
                    },
                    "contents":{
                        "__TYPE":"Array",
                        "contents":[
                            {
                                "ElementName":"Source",
                                "targetUninit":{
                                    "id":"Trigger:复活玩家:4041195397",
                                    "packageName":"busiyixiantu_5n1b",
                                    "s_or_c":"server"
                                }
                            },
                            {
                                "ElementName":"Source",
                                "targetUninit":{
                                    "id":"Trigger:测试用:91970509",
                                    "packageName":"busiyixiantu_5n1b",
                                    "s_or_c":"server"
                                }
                            }
                        ]
                    },
                    "displayName":"",
                    "flags":{
                    },
                    "name":"通用触发",
                    "rankOrder":18,
                    "staticWarningMsgs":{
                        "__TYPE":"Array",
                        "contents":{
                        }
                    },
                    "tips":""
                }
            ]
        },
        "displayName":"",
        "flags":{
        },
        "name":"busiyixiantu_5n1b",
        "s_or_c":"server",
        "staticWarningMsgs":{
            "__TYPE":"Array",
            "contents":{
            }
        },
        "tips":""
    },
    "id":"ENV:server Module:busiyixiantu_5n1b",
    "keyword":"",
    "name":"busiyixiantu_5n1b",
    "packageName":"busiyixiantu_5n1b",
    "rankOrder":0,
    "s_or_c":"server",
    "staticWarningMsgs":{
        "__TYPE":"Array",
        "contents":{
        }
    },
    "tips":"",
    "type":{
        "ElementName":"ModuleType",
        "breakPointInfo":{
            "disabled":false,
            "hasBreakPoint":false,
            "type":2
        },
        "displayName":"",
        "flags":{
        },
        "source":{
            "ElementName":"Source",
            "targetUninit":{
                "id":"ENV:server Module:busiyixiantu_5n1b",
                "packageName":"busiyixiantu_5n1b",
                "s_or_c":"server"
            }
        },
        "staticWarningMsgs":{
            "__TYPE":"Array",
            "contents":{
            }
        },
        "tips":""
    },
    "v2_version":0.500000
}